gris/__init__.py
gris/__main__.py
gris/bibtex.py
gris/gris.py
gris/io.py
gris/wos.py
gris-0.8.0.dist-info/LICENSE.txt
gris-0.8.0.dist-info/METADATA
gris-0.8.0.dist-info/WHEEL
gris-0.8.0.dist-info/top_level.txt
gris-0.8.0.dist-info/RECORD
