Metadata-Version: 2.1
Name: gris
Version: 0.8.0
Summary: Parser of RIS file format
Author: Angel Yanguas-Gil
Project-URL: Homepage, https://github.com/anglyan/gris.git
Project-URL: docs, https://gris.readthedocs.io/en/latest/index.html
Keywords: RIS file format,RefMan RIS,bibliography,parser
Classifier: Programming Language :: Python :: 3
Classifier: Development Status :: 4 - Beta
Classifier: License :: OSI Approved :: GNU General Public License v2 or later (GPLv2+)
Classifier: Operating System :: OS Independent
Classifier: Environment :: Console
Classifier: Topic :: Scientific/Engineering
Classifier: Topic :: Utilities
License-File: LICENSE.txt
